SQLPanda/__init__.py
SQLPanda/scripts.py
SQLPanda/BigPanda/__init__.py
SQLPanda/BigPanda/bigpanda.py
SQLPanda/LitePanda/__init__.py
SQLPanda/LitePanda/litepanda.py
SQLPanda/api/__init__.py
SQLPanda/api/api.py
sql_panda_wrapper-0.2.1.dist-info/METADATA
sql_panda_wrapper-0.2.1.dist-info/WHEEL
sql_panda_wrapper-0.2.1.dist-info/top_level.txt
sql_panda_wrapper-0.2.1.dist-info/RECORD
