Metadata-Version: 2.1
Name: sql-panda-wrapper
Version: 0.2.1
Summary: Panda wrapper for SQLite
Home-page: https://github.com/nsragow/SQLPanda
Author: Noah Sragow
Author-email: nsragow@gmail.com
License: MIT
Platform: UNKNOWN
